{"https://github.com/TheAlgorithms/Python": {"/arithmetic_analysis/bisection.py": ["bisection", "f"], "/arithmetic_analysis/gaussian_elimination.py": ["retroactive_resolution", "gaussian_elimination"], "/arithmetic_analysis/in_static_equilibrium.py": ["polar_force", "in_static_equilibrium"], "/arithmetic_analysis/intersection.py": ["intersection", "f"], "/arithmetic_analysis/jacobi_iteration_method.py": ["jacobi_iteration_method", "strictly_diagonally_dominant"], "/arithmetic_analysis/lu_decomposition.py": ["lower_upper_decomposition"], "/arithmetic_analysis/newton_forward_interpolation.py": ["ucal", "main"], "/arithmetic_analysis/newton_method.py": ["newton", "f", "f1"], "/arithmetic_analysis/newton_raphson.py": ["newton_raphson"], "/arithmetic_analysis/secant_method.py": ["f", "secant_method"], "/audio_filters/butterworth_filter.py": ["make_lowpass", "make_highpass", "make_bandpass", "make_allpass", "make_peak", "make_lowshelf", "make_highshelf"], "/audio_filters/iir_filter.py": ["set_coefficients", "process"], "/audio_filters/show_response.py": ["process", "get_bounds", "show_frequency_response", "show_phase_response"], "/backtracking/all_combinations.py": ["generate_all_combinations", "create_all_state", "print_all_state"], "/backtracking/all_permutations.py": ["generate_all_permutations", "create_state_space_tree"], "/backtracking/all_subsequences.py": ["generate_all_subsequences", "create_state_space_tree"], "/backtracking/coloring.py": ["valid_coloring", "util_color", "color"], "/backtracking/hamiltonian_cycle.py": ["valid_connection", "util_hamilton_cycle", "hamilton_cycle"], "/backtracking/knight_tour.py": ["get_valid_pos", "is_complete", "open_knight_tour_helper", "open_knight_tour"], "/backtracking/minimax.py": ["minimax", "main"], "/backtracking/n_queens.py": ["isSafe", "solve", "printboard"], "/backtracking/n_queens_math.py": ["depth_first_search", "n_queens_solution"], "/backtracking/rat_in_maze.py": ["solve_maze", "run_maze"], "/backtracking/sudoku.py": ["is_safe", "find_empty_location", "sudoku", "print_solution"], "/backtracking/sum_of_subsets.py": ["generate_sum_of_subsets_soln", "create_state_space_tree"], "/bit_manipulation/binary_and_operator.py": ["binary_and"], "/bit_manipulation/binary_count_setbits.py": ["binary_count_setbits"], "/bit_manipulation/binary_count_trailing_zeros.py": ["binary_count_trailing_zeros"], "/bit_manipulation/binary_or_operator.py": ["binary_or"], "/bit_manipulation/binary_shifts.py": ["logical_left_shift", "logical_right_shift", "arithmetic_right_shift"], "/bit_manipulation/binary_twos_complement.py": ["twos_complement"], "/bit_manipulation/binary_xor_operator.py": ["binary_xor"], "/bit_manipulation/count_1s_brian_kernighan_method.py": ["get_1s_count"], "/bit_manipulation/count_number_of_one_bits.py": ["get_set_bits_count"], "/bit_manipulation/gray_code_sequence.py": ["gray_code", "gray_code_sequence_string"], "/bit_manipulation/reverse_bits.py": ["get_reverse_bit_string", "reverse_bit"], "/bit_manipulation/single_bit_manipulation_operations.py": ["set_bit", "clear_bit", "flip_bit", "is_bit_set", "get_bit"], "/blockchain/chinese_remainder_theorem.py": ["extended_euclid", "chinese_remainder_theorem", "invert_modulo", "chinese_remainder_theorem2"], "/blockchain/diophantine_equation.py": ["diophantine", "diophantine_all_soln", "greatest_common_divisor", "extended_gcd"], "/blockchain/modular_division.py": ["modular_division", "invert_modulo", "modular_division2", "extended_gcd", "extended_euclid", "greatest_common_divisor"], "/boolean_algebra/quine_mc_cluskey.py": ["compare_string", "check", "decimal_to_binary", "is_for_table", "selection", "prime_implicant_chart", "main"], "/cellular_automata/conways_game_of_life.py": ["new_generation", "generate_images"], "/cellular_automata/game_of_life.py": ["create_canvas", "seed", "run", "__judge_point"], "/cellular_automata/nagel_schrekenberg.py": ["construct_highway", "get_distance", "update", "simulate"], "/cellular_automata/one_dimensional.py": ["format_ruleset", "new_generation", "generate_image"], "/ciphers/a1z26.py": ["encode", "decode", "main"], "/ciphers/affine_cipher.py": ["check_keys", "encrypt_message", "decrypt_message", "get_random_key", "main"], "/ciphers/atbash.py": ["atbash_slow", "atbash", "benchmark"], "/ciphers/baconian_cipher.py": ["encode", "decode"], "/ciphers/base16.py": ["base16_encode", "base16_decode"], "/ciphers/base32.py": ["base32_encode", "base32_decode"], "/ciphers/base64.py": ["base64_encode", "base64_decode"], "/ciphers/base85.py": ["base85_encode", "base85_decode"], "/ciphers/beaufort_cipher.py": ["generate_key", "cipher_text", "original_text", "main"], "/ciphers/bifid.py": ["letter_to_numbers", "numbers_to_letter", "encode", "decode"], "/ciphers/brute_force_caesar_cipher.py": ["decrypt", "main"], "/ciphers/caesar_cipher.py": ["encrypt", "decrypt", "brute_force"], "/ciphers/cryptomath_module.py": ["gcd", "find_mod_inverse"], "/ciphers/decrypt_caesar_with_chi_squared.py": ["decrypt_caesar_with_chi_squared", "chi_squared_statistic_values_sorting_key"], "/ciphers/deterministic_miller_rabin.py": ["miller_rabin", "test_miller_rabin"], "/ciphers/diffie.py": ["find_primitive"], "/ciphers/diffie_hellman.py": ["get_private_key", "generate_public_key", "is_valid_public_key", "generate_shared_key", "is_valid_public_key_static", "generate_shared_key_static"], "/ciphers/elgamal_key_generator.py": ["primitive_root", "generate_key", "make_key_files", "main"], "/ciphers/enigma_machine2.py": ["_validator", "_plugboard", "enigma"], "/ciphers/hill_cipher.py": ["greatest_common_divisor", "replace_letters", "replace_digits", "check_determinant", "process_text", "encrypt", "make_decrypt_key", "decrypt", "main"], "/ciphers/mixed_keyword_cypher.py": ["mixed_keyword"], "/ciphers/mono_alphabetic_ciphers.py": ["translate_message", "encrypt_message", "decrypt_message", "main"], "/ciphers/morse_code.py": ["encrypt", "decrypt", "main"], "/ciphers/onepad_cipher.py": ["encrypt", "decrypt"], "/ciphers/playfair_cipher.py": ["chunker", "prepare_input", "generate_table", "encode", "decode"], "/ciphers/polybius.py": ["letter_to_numbers", "numbers_to_letter", "encode", "decode"], "/ciphers/porta_cipher.py": ["generate_table", "encrypt", "decrypt", "get_position", "get_opponent"], "/ciphers/rabin_miller.py": ["rabinMiller", "isPrime", "generateLargePrime"], "/ciphers/rail_fence_cipher.py": ["encrypt", "decrypt", "bruteforce"], "/ciphers/rot13.py": ["dencrypt", "main"], "/ciphers/rsa_cipher.py": ["get_blocks_from_text", "get_text_from_blocks", "encrypt_message", "decrypt_message", "read_key_file", "encrypt_and_write_to_file", "read_from_file_and_decrypt", "main"], "/ciphers/rsa_factorization.py": ["rsafactor"], "/ciphers/rsa_key_generator.py": ["main", "generateKey", "makeKeyFiles"], "/ciphers/shuffled_shift_cipher.py": ["__str__", "__neg_pos", "__passcode_creator", "__make_key_list", "__make_shift_key", "decrypt", "encrypt", "test_end_to_end"], "/ciphers/simple_keyword_cypher.py": ["remove_duplicates", "create_cipher_map", "encipher", "decipher", "main"], "/ciphers/simple_substitution_cipher.py": ["main", "checkValidKey", "encryptMessage", "decryptMessage", "translateMessage", "getRandomKey"], "/ciphers/trafid_cipher.py": ["__encryptPart", "__decryptPart", "__prepare", "encryptMessage", "decryptMessage"], "/ciphers/transposition_cipher.py": ["main", "encryptMessage", "decryptMessage"], "/ciphers/transposition_cipher_encrypt_decrypt_file.py": ["main"], "/ciphers/vigenere_cipher.py": ["main", "encryptMessage", "decryptMessage", "translateMessage"], "/ciphers/xor_cipher.py": ["encrypt", "decrypt", "encrypt_string", "decrypt_string", "encrypt_file", "decrypt_file"], "/compression/burrows_wheeler.py": ["all_rotations", "bwt_transform", "reverse_bwt"], "/compression/huffman.py": ["__repr__", "parse_file", "build_tree", "traverse_tree", "huffman"], "/compression/lempel_ziv.py": ["read_file_binary", "add_key_to_lexicon", "compress_data", "add_file_length", "write_file_binary", "compress"], "/compression/lempel_ziv_decompress.py": ["read_file_binary", "decompress_data", "write_file_binary", "remove_prefix", "compress"], "/compression/peak_signal_to_noise_ratio.py": ["psnr", "main"], "/computer_vision/flip_augmentation.py": ["main", "get_dataset", "update_image_and_anno", "random_chars"], "/computer_vision/harris_corner.py": ["__str__", "detect"], "/computer_vision/mean_threshold.py": ["mean_threshold"], "/computer_vision/mosaic_augmentation.py": ["main", "get_dataset", "update_image_and_anno", "random_chars"], "/computer_vision/pooling_functions.py": ["maxpooling", "avgpooling"], "/conversions/binary_to_decimal.py": ["bin_to_decimal"], "/conversions/binary_to_hexadecimal.py": ["bin_to_hexadecimal"], "/conversions/binary_to_octal.py": ["bin_to_octal"], "/conversions/decimal_to_any.py": ["decimal_to_any"], "/conversions/decimal_to_binary.py": ["decimal_to_binary"], "/conversions/decimal_to_binary_recursion.py": ["binary_recursive", "main"], "/conversions/decimal_to_hexadecimal.py": ["decimal_to_hexadecimal"], "/conversions/decimal_to_octal.py": ["decimal_to_octal", "main"], "/conversions/hex_to_bin.py": ["hex_to_bin"], "/conversions/hexadecimal_to_decimal.py": ["hex_to_decimal"], "/conversions/length_conversion.py": ["length_conversion"], "/conversions/molecular_chemistry.py": ["molarity_to_normality", "moles_to_pressure", "moles_to_volume", "pressure_and_volume_to_temperature"], "/conversions/octal_to_decimal.py": ["oct_to_decimal"], "/conversions/prefix_conversions.py": ["convert_si_prefix", "convert_binary_prefix"], "/conversions/pressure_conversions.py": ["pressure_conversion"], "/conversions/rgb_hsv_conversion.py": ["hsv_to_rgb", "rgb_to_hsv", "approximately_equal_hsv"], "/conversions/roman_numerals.py": ["roman_to_int", "int_to_roman"], "/conversions/temperature_conversions.py": ["celsius_to_fahrenheit", "celsius_to_kelvin", "celsius_to_rankine", "fahrenheit_to_celsius", "fahrenheit_to_kelvin", "fahrenheit_to_rankine", "kelvin_to_celsius", "kelvin_to_fahrenheit", "kelvin_to_rankine", "rankine_to_celsius", "rankine_to_fahrenheit", "rankine_to_kelvin", "reaumur_to_kelvin", "reaumur_to_fahrenheit", "reaumur_to_celsius", "reaumur_to_rankine"], "/conversions/volume_conversions.py": ["volume_conversion"], "/conversions/weight_conversion.py": ["weight_conversion"], "/data_structures/binary_tree/avl_tree.py": ["get_height", "del_node", "is_empty", "push", "pop", "count", "print", "get_data", "get_left", "get_right", "set_data", "set_left", "set_right", "set_height", "my_max", "right_rotation", "left_rotation", "lr_rotation", "rl_rotation", "insert_node", "get_rightMost", "get_leftMost", "insert", "__str__", "_test"], "/data_structures/binary_tree/basic_binary_tree.py": ["display", "depth_of_tree", "is_full_binary_tree", "main"], "/data_structures/binary_tree/binary_search_tree.py": ["__repr__", "__str__", "__reassign_nodes", "is_right", "empty", "__insert", "insert", "search", "get_max", "get_min", "remove", "preorder_traverse", "traversal_tree", "inorder", "find_kth_smallest", "postorder", "binary_search_tree"], "/data_structures/binary_tree/binary_search_tree_recursive.py": ["empty", "is_empty", "put", "_put", "search", "_search", "remove", "_reassign_nodes", "_get_lowest_node", "exists", "get_max_label", "get_min_label", "inorder_traversal", "_inorder_traversal", "preorder_traversal", "_preorder_traversal", "_get_binary_search_tree", "test_put", "test_search", "test_remove", "test_remove_2", "test_empty", "test_is_empty", "test_exists", "test_get_max_label", "test_get_min_label", "test_inorder_traversal", "test_preorder_traversal", "binary_search_tree_example"], "/data_structures/binary_tree/binary_tree_mirror.py": ["binary_tree_mirror_dict", "binary_tree_mirror"], "/data_structures/binary_tree/binary_tree_traversals.py": ["populate_output", "make_tree", "preorder", "postorder", "inorder", "height", "level_order", "get_nodes_from_left_to_right", "get_nodes_from_right_to_left", "zigzag", "main"], "/data_structures/binary_tree/fenwick_tree.py": ["update", "query"], "/data_structures/binary_tree/lazy_segment_tree.py": ["left", "right", "build", "update", "query", "__str__"], "/data_structures/binary_tree/lowest_common_ancestor.py": ["swap", "create_sparse", "lowest_common_ancestor", "breadth_first_search", "main"], "/data_structures/binary_tree/merge_two_binary_trees.py": ["merge_two_binary_trees", "print_preorder"], "/data_structures/binary_tree/non_recursive_segment_tree.py": ["build", "update", "query", "test_all_segments"], "/data_structures/binary_tree/number_of_possible_binary_trees.py": ["binomial_coefficient", "catalan_number", "factorial", "binary_tree_count"], "/data_structures/binary_tree/red_black_tree.py": ["rotate_left", "rotate_right", "insert", "_insert_repair", "remove", "_remove_repair", "check_color_properties", "check_coloring", "black_height", "__contains__", "search", "floor", "ceil", "get_max", "get_min", "grandparent", "sibling", "is_left", "is_right", "__bool__", "preorder_traverse", "inorder_traverse", "postorder_traverse", "__repr__", "__eq__", "color", "test_rotations", "test_insertion_speed", "test_insert", "test_insert_and_search", "test_insert_delete", "test_floor_ceil", "test_min_max", "test_tree_traversal", "test_tree_chaining", "print_results", "pytests", "main"], "/data_structures/binary_tree/segment_tree.py": ["left", "right", "build", "update", "update_recursive", "query", "query_recursive", "showData"], "/data_structures/binary_tree/segment_tree_other.py": ["__str__", "update", "query_range", "_build_tree", "_update_tree", "_query_range", "traverse"], "/data_structures/binary_tree/treap.py": ["__repr__", "__str__", "split", "merge", "insert", "erase", "inorder", "interactTreap", "main"], "/data_structures/binary_tree/wavelet_tree.py": ["__repr__", "build_tree", "rank_till_index", "rank", "quantile", "range_counting"], "/data_structures/disjoint_set/alternate_disjoint_set.py": ["merge", "get_parent"], "/data_structures/disjoint_set/disjoint_set.py": ["make_set", "union_set", "find_set", "find_python_set", "test_disjoint_set"], "/data_structures/hashing/double_hash.py": ["__hash_function_2", "__hash_double_function", "_collision_resolution"], "/data_structures/hashing/hash_table.py": ["keys", "balanced_factor", "hash_function", "_step_by_step", "bulk_insert", "_set_value", "_collision_resolution", "rehashing", "insert_data"], "/data_structures/hashing/hash_table_with_linked_list.py": ["_set_value", "balanced_factor", "_collision_resolution"], "/data_structures/hashing/number_theory/prime_numbers.py": ["check_prime", "next_prime"], "/data_structures/hashing/quadratic_probing.py": ["_collision_resolution"], "/data_structures/heap/binomial_heap.py": ["mergeTrees", "mergeHeaps", "insert", "peek", "isEmpty", "deleteMin", "preOrder", "__traversal", "__str__"], "/data_structures/heap/heap.py": ["__repr__", "parent_index", "left_child_idx", "right_child_idx", "max_heapify", "build_max_heap", "max", "extract_max", "insert", "heap_sort"], "/data_structures/heap/heap_generic.py": ["_parent", "_left", "_right", "_swap", "_cmp", "_get_valid_parent", "_heapify_up", "_heapify_down", "update_item", "delete_item", "insert_item", "get_top", "extract_top", "test_heap"], "/data_structures/heap/max_heap.py": ["__swap_up", "insert", "__swap_down", "pop", "get_list"], "/data_structures/heap/min_heap.py": ["__str__", "__lt__", "__getitem__", "get_parent_idx", "get_left_child_idx", "get_right_child_idx", "get_value", "build_heap", "sift_down", "sift_up", "peek", "remove", "insert", "is_empty", "decrease_key"], "/data_structures/heap/randomized_heap.py": ["value", "merge", "insert", "pop", "top", "clear", "to_sorted_list", "__bool__"], "/data_structures/heap/skew_heap.py": ["value", "merge", "__bool__", "__iter__", "insert", "pop", "top", "clear"], "/data_structures/linked_list/__init__.py": ["add", "remove", "is_empty", "__str__"], "/data_structures/linked_list/circular_linked_list.py": ["__iter__", "__repr__", "insert_tail", "insert_head", "insert_nth", "delete_front", "delete_tail", "delete_nth", "is_empty", "test_circular_linked_list"], "/data_structures/linked_list/deque_doubly.py": ["has_next_and_prev", "is_empty", "_insert", "_delete", "first", "last", "add_first", "add_last", "remove_first", "remove_last"], "/data_structures/linked_list/doubly_linked_list.py": ["__str__", "__iter__", "insert_at_head", "insert_at_tail", "insert_at_nth", "delete_head", "delete_tail", "delete_at_nth", "delete", "is_empty", "test_doubly_linked_list"], "/data_structures/linked_list/doubly_linked_list_two.py": ["__str__", "__iter__", "get_data", "get_next", "get_previous", "__next__", "__contains__", "get_head_data", "get_tail_data", "set_head", "set_tail", "insert", "insert_before_node", "insert_after_node", "insert_at_position", "get_node", "delete_value", "remove_node_pointers", "is_empty", "create_linked_list"], "/data_structures/linked_list/from_sequence.py": ["__repr__", "make_linked_list"], "/data_structures/linked_list/has_loop.py": ["__iter__", "has_loop"], "/data_structures/linked_list/is_palindrome.py": ["is_palindrome", "is_palindrome_stack", "is_palindrome_dict"], "/data_structures/linked_list/merge_two_lists.py": ["__iter__", "__str__", "merge_lists"], "/data_structures/linked_list/middle_element_of_linked_list.py": ["push", "middle_element"], "/data_structures/linked_list/print_reverse.py": ["__repr__", "make_linked_list", "print_reverse", "main"], "/data_structures/linked_list/singly_linked_list.py": ["__repr__", "__iter__", "__getitem__", "__setitem__", "insert_tail", "insert_head", "insert_nth", "print_list", "delete_head", "delete_tail", "delete_nth", "is_empty", "reverse", "test_singly_linked_list", "test_singly_linked_list_2", "main"], "/data_structures/linked_list/skip_list.py": ["__repr__", "level", "__str__", "__iter__", "random_level", "_locate_node", "delete", "insert", "find", "test_insert", "test_insert_overrides_existing_value", "test_searching_empty_list_returns_none", "test_search", "test_deleting_item_from_empty_list_do_nothing", "test_deleted_items_are_not_founded_by_find_method", "test_delete_removes_only_given_key", "test_delete_doesnt_leave_dead_nodes", "traverse_keys", "test_iter_always_yields_sorted_values", "is_sorted", "pytests", "main"], "/data_structures/linked_list/swap_nodes.py": ["print_list", "push", "swap_nodes"], "/data_structures/queue/circular_queue.py": ["is_empty", "first", "enqueue", "dequeue"], "/data_structures/queue/circular_queue_linked_list.py": ["create_linked_list", "is_empty", "first", "enqueue", "dequeue", "check_can_perform_operation", "check_is_full"], "/data_structures/queue/double_ended_queue.py": ["__iter__", "__next__", "append", "appendleft", "extend", "extendleft", "pop", "popleft", "is_empty", "__eq__", "__repr__"], "/data_structures/queue/linked_queue.py": ["__str__", "__iter__", "is_empty", "put", "get", "clear"], "/data_structures/queue/priority_queue_using_list.py": ["enqueue", "dequeue", "__str__", "fixed_priority_queue", "element_priority_queue"], "/data_structures/queue/queue_on_list.py": ["__str__", "put", "get", "rotate", "get_front", "size"], "/data_structures/queue/queue_on_pseudo_stack.py": ["__str__", "put", "get", "rotate", "front", "size"], "/data_structures/stacks/balanced_parentheses.py": ["balanced_parentheses"], "/data_structures/stacks/dijkstras_two_stack_algorithm.py": ["dijkstras_two_stack_algorithm"], "/data_structures/stacks/evaluate_postfix_notations.py": ["evaluate_postfix"], "/data_structures/stacks/infix_to_postfix_conversion.py": ["precedence", "infix_to_postfix"], "/data_structures/stacks/infix_to_prefix_conversion.py": ["infix_2_postfix", "infix_2_prefix"], "/data_structures/stacks/next_greater_element.py": ["next_greatest_element_slow", "next_greatest_element_fast", "next_greatest_element"], "/data_structures/stacks/postfix_evaluation.py": ["Solve"], "/data_structures/stacks/prefix_evaluation.py": ["is_operand", "evaluate"], "/data_structures/stacks/stack.py": ["__bool__", "__str__", "push", "pop", "peek", "is_empty", "is_full", "size", "__contains__", "test_stack"], "/data_structures/stacks/stack_with_doubly_linked_list.py": ["push", "pop", "top", "is_empty", "print_stack"], "/data_structures/stacks/stack_with_singly_linked_list.py": ["__str__", "__iter__", "is_empty", "push", "pop", "peek", "clear"], "/data_structures/stacks/stock_span_problem.py": ["calculateSpan", "printArray"], "/data_structures/trie/trie.py": ["insert_many", "insert", "find", "delete", "_delete", "print_words", "test_trie", "print_results", "pytests", "main"], "/digital_image_processing/change_brightness.py": ["change_brightness", "brightness"], "/digital_image_processing/change_contrast.py": ["change_contrast", "contrast"], "/digital_image_processing/convert_to_negative.py": ["convert_to_negative"], "/digital_image_processing/dithering/burkes.py": ["get_greyscale", "process"], "/digital_image_processing/edge_detection/canny.py": ["gen_gaussian_kernel", "canny"], "/digital_image_processing/filters/bilateral_filter.py": ["vec_gaussian", "get_slice", "get_gauss_kernel", "bilateral_filter", "parse_args"], "/digital_image_processing/filters/convolve.py": ["im2col", "img_convolve"], "/digital_image_processing/filters/gabor_filter.py": ["gabor_filter_kernel"], "/digital_image_processing/filters/gaussian_filter.py": ["gen_gaussian_kernel", "gaussian_filter"], "/digital_image_processing/filters/median_filter.py": ["median_filter"], "/digital_image_processing/filters/sobel_filter.py": ["sobel_filter"], "/digital_image_processing/histogram_equalization/histogram_stretch.py": ["stretch", "plotHistogram", "showImage"], "/digital_image_processing/index_calculation.py": ["setMatrices", "calculation", "ARVI2", "CCCI", "CVI", "GLI", "NDVI", "BNDVI", "redEdgeNDVI", "GNDVI", "GBNDVI", "GRNDVI", "RBNDVI", "PNDVI", "ATSAVI", "BWDRVI", "CIgreen", "CIrededge", "CI", "CTVI", "GDVI", "EVI", "GEMI", "GOSAVI", "GSAVI", "Hue", "IVI", "IPVI", "I", "RVI", "MRVI", "MSAVI", "NormG", "NormNIR", "NormR", "NGRDI", "RI", "S", "IF", "DVI", "TVI", "NDRE"], "/digital_image_processing/morphological_operations/dilation_operation.py": ["rgb2gray", "gray2binary", "dilation"], "/digital_image_processing/morphological_operations/erosion_operation.py": ["rgb2gray", "gray2binary", "erosion"], "/digital_image_processing/resize/resize.py": ["process", "get_x", "get_y"], "/digital_image_processing/rotation/rotation.py": ["get_rotation"], "/digital_image_processing/sepia.py": ["make_sepia", "to_grayscale", "normalize"], "/digital_image_processing/test_digital_image_processing.py": ["test_convert_to_negative", "test_change_contrast", "test_gen_gaussian_kernel", "test_canny", "test_gen_gaussian_kernel_filter", "test_convolve_filter", "test_median_filter", "test_sobel_filter", "test_sepia", "test_burkes", "test_nearest_neighbour"], "/divide_and_conquer/closest_pair_of_points.py": ["euclidean_distance_sqr", "column_based_sort", "dis_between_closest_pair", "dis_between_closest_in_strip", "closest_pair_of_points_sqr", "closest_pair_of_points"], "/divide_and_conquer/convex_hull.py": ["__eq__", "__ne__", "__gt__", "__lt__", "__ge__", "__le__", "__repr__", "__hash__", "_construct_points", "_validate_input", "_det", "convex_hull_bf", "convex_hull_recursive", "_construct_hull", "convex_hull_melkman", "main"], "/divide_and_conquer/heaps_algorithm.py": ["heaps", "generate"], "/divide_and_conquer/heaps_algorithm_iterative.py": ["heaps", "generate"], "/divide_and_conquer/inversions.py": ["count_inversions_bf", "count_inversions_recursive", "_count_cross_inversions", "main"], "/divide_and_conquer/kth_order_statistic.py": ["random_pivot", "kth_number"], "/divide_and_conquer/max_difference_pair.py": ["max_difference"], "/divide_and_conquer/max_subarray_sum.py": ["max_sum_from_start", "max_cross_array_sum", "max_subarray_sum"], "/divide_and_conquer/mergesort.py": ["merge", "merge_sort"], "/divide_and_conquer/peak.py": ["peak"], "/divide_and_conquer/power.py": ["actual_power", "power"], "/divide_and_conquer/strassen_matrix_multiplication.py": ["default_matrix_multiplication", "matrix_addition", "matrix_subtraction", "split_matrix", "matrix_dimensions", "print_matrix", "actual_strassen", "strassen"], "/dynamic_programming/abbreviation.py": ["abbr"], "/dynamic_programming/all_construct.py": ["all_construct"], "/dynamic_programming/bitmask.py": ["CountWaysUtil", "countNoOfWays"], "/dynamic_programming/catalan_numbers.py": ["catalan_numbers"], "/dynamic_programming/climbing_stairs.py": ["climb_stairs"], "/dynamic_programming/edit_distance.py": ["__prepare__", "__solveDP", "solve", "min_distance_bottom_up"], "/dynamic_programming/factorial.py": ["factorial"], "/dynamic_programming/fast_fibonacci.py": ["fibonacci", "_fib"], "/dynamic_programming/fibonacci.py": ["get", "main"], "/dynamic_programming/floyd_warshall.py": ["addEdge", "floyd_warshall", "showMin"], "/dynamic_programming/fractional_knapsack.py": ["fracKnapsack"], "/dynamic_programming/fractional_knapsack_2.py": ["fractional_knapsack"], "/dynamic_programming/integer_partition.py": ["partition"], "/dynamic_programming/iterating_through_submasks.py": ["list_of_submasks"], "/dynamic_programming/knapsack.py": ["MF_knapsack", "knapsack", "knapsack_with_example_solution", "_construct_solution"], "/dynamic_programming/longest_common_subsequence.py": ["longest_common_subsequence"], "/dynamic_programming/longest_increasing_subsequence.py": ["longest_subsequence"], "/dynamic_programming/longest_increasing_subsequence_o(nlogn).py": ["CeilIndex", "LongestIncreasingSubsequenceLength"], "/dynamic_programming/longest_sub_array.py": ["solve_sub_array"], "/dynamic_programming/matrix_chain_order.py": ["MatrixChainOrder", "PrintOptimalSolution", "main"], "/dynamic_programming/max_non_adjacent_sum.py": ["maximum_non_adjacent_sum"], "/dynamic_programming/max_sub_array.py": ["find_max_sub_array", "find_max_cross_sum", "max_sub_array"], "/dynamic_programming/max_sum_contiguous_subsequence.py": ["max_subarray_sum"], "/dynamic_programming/minimum_coin_change.py": ["dp_count"], "/dynamic_programming/minimum_cost_path.py": ["minimum_cost_path"], "/dynamic_programming/minimum_partition.py": ["findMin"], "/dynamic_programming/minimum_steps_to_one.py": ["min_steps_to_one"], "/dynamic_programming/optimal_binary_search_tree.py": ["__str__", "print_binary_search_tree", "find_optimal_binary_search_tree", "main"], "/dynamic_programming/rod_cutting.py": ["naive_cut_rod_recursive", "top_down_cut_rod", "_top_down_cut_rod_recursive", "bottom_up_cut_rod", "_enforce_args", "main"], "/dynamic_programming/subset_generation.py": ["combination_util", "print_combination"], "/dynamic_programming/sum_of_subset.py": ["isSumSubset"], "/electronics/carrier_concentration.py": ["carrier_concentration"], "/electronics/coulombs_law.py": ["couloumbs_law"], "/electronics/electric_power.py": ["electric_power"], "/electronics/ohms_law.py": ["ohms_law"], "/file_transfer/send_file.py": ["send_file"], "/file_transfer/tests/test_send_file.py": ["test_send_file_running_as_expected"], "/financial/equated_monthly_installments.py": ["equated_monthly_installments"], "/financial/interest.py": ["simple_interest", "compound_interest"], "/fractals/julia_sets.py": ["eval_exponential", "eval_quadratic_polynomial", "prepare_grid", "iterate_function", "show_results", "ignore_overflow_warnings"], "/fractals/koch_snowflake.py": ["iterate", "iteration_step", "rotate", "plot"], "/fractals/mandelbrot.py": ["get_distance", "get_black_and_white_rgb", "get_color_coded_rgb", "get_image"], "/fractals/sierpinski_triangle.py": ["getMid", "triangle"], "/genetic_algorithm/basic_string.py": ["basic", "evaluate", "select", "crossover", "mutate"], "/geodesy/haversine_distance.py": ["haversine_distance"], "/geodesy/lamberts_ellipsoidal_distance.py": ["lamberts_ellipsoidal_distance"], "/graphics/bezier_curve.py": ["basis_function", "bezier_curve_function", "plot_curve"], "/graphics/vector3_for_2d_rendering.py": ["convert_to_2d", "rotate"], "/graphs/a_star.py": ["search"], "/graphs/articulation_points.py": ["computeAP", "dfs"], "/graphs/basic_graphs.py": ["_input", "initialize_unweighted_directed_graph", "initialize_unweighted_undirected_graph", "initialize_weighted_undirected_graph", "dfs", "bfs", "dijk", "topo", "adjm", "floy", "prim", "edglist", "krusk", "find_isolated_nodes"], "/graphs/bellman_ford.py": ["print_distance", "check_negative_cycle", "bellman_ford"], "/graphs/bfs_shortest_path.py": ["bfs_shortest_path", "bfs_shortest_path_distance"], "/graphs/bfs_zero_one_shortest_path.py": ["__getitem__", "size", "add_edge", "get_shortest_path"], "/graphs/bidirectional_a_star.py": ["search", "calculate_heuristic", "__lt__", "get_successors", "retrace_path", "retrace_bidirectional_path"], "/graphs/bidirectional_breadth_first_search.py": ["search", "get_successors", "retrace_path", "retrace_bidirectional_path"], "/graphs/boruvka.py": ["add_edge", "find_component", "set_component", "union", "boruvka", "test_vector"], "/graphs/breadth_first_search.py": ["print_graph", "add_edge", "bfs"], "/graphs/breadth_first_search_2.py": ["breadth_first_search"], "/graphs/breadth_first_search_shortest_path.py": ["breath_first_search", "shortest_path"], "/graphs/check_bipartite_graph_bfs.py": ["checkBipartite", "bfs"], "/graphs/check_bipartite_graph_dfs.py": ["check_bipartite_dfs", "dfs"], "/graphs/check_cycle.py": ["check_cycle", "depth_first_search"], "/graphs/connected_components.py": ["dfs", "connected_components"], "/graphs/depth_first_search.py": ["depth_first_search"], "/graphs/depth_first_search_2.py": ["print_graph", "add_edge", "dfs", "dfs_recursive"], "/graphs/dijkstra.py": ["dijkstra"], "/graphs/dijkstra_2.py": ["printDist", "minDist", "Dijkstra"], "/graphs/dijkstra_algorithm.py": ["isEmpty", "min_heapify", "insert", "extract_min", "left", "right", "par", "swap", "decrease_key", "add_edge", "show_graph", "dijkstra", "show_distances", "show_path"], "/graphs/dinic.py": ["add_edge", "depth_first_search", "max_flow"], "/graphs/directed_and_undirected_(weighted)_graph.py": ["add_pair", "all_nodes", "remove_pair", "dfs", "fill_graph_randomly", "bfs", "cycle_nodes", "has_cycle", "dfs_time", "bfs_time", "in_degree", "out_degree", "topological_sort", "degree"], "/graphs/edmonds_karp_multiple_source_and_sink.py": ["_algorithm", "_normalizeGraph", "findMaximumFlow", "setMaximumFlowAlgorithm", "execute", "getMaximumFlow", "processVertex", "push", "relabel"], "/graphs/eulerian_path_and_circuit_for_undirected_graph.py": ["dfs", "check_circuit_or_path", "check_euler", "main"], "/graphs/even_tree.py": ["dfs", "even_tree"], "/graphs/finding_bridges.py": ["__get_demo_graph", "compute_bridges", "dfs"], "/graphs/frequent_pattern_graph_miner.py": ["get_distinct_edge", "get_bitcode", "get_frequency_table", "get_nodes", "get_cluster", "get_support", "print_all", "create_edge", "construct_graph", "myDFS", "find_freq_subgraph_given_support", "freq_subgraphs_edge_list", "preprocess"], "/graphs/g_topological_sort.py": ["print_stack", "depth_first_search", "topological_sort"], "/graphs/gale_shapley_bigraph.py": ["stable_matching"], "/graphs/graph_list.py": ["add_edge", "__repr__"], "/graphs/graph_matrix.py": ["add_edge", "show"], "/graphs/graphs_floyd_warshall.py": ["_print_dist", "floyd_warshall"], "/graphs/greedy_best_first.py": ["calculate_heuristic", "__lt__", "search", "get_successors", "retrace_path"], "/graphs/greedy_min_vertex_cover.py": ["greedy_min_vertex_cover"], "/graphs/kahns_algorithm_long.py": ["longestDistance"], "/graphs/kahns_algorithm_topo.py": ["topologicalSort"], "/graphs/karger.py": ["partition_graph"], "/graphs/markov_chain.py": ["add_node", "add_transition_probability", "get_nodes", "transition", "get_transitions"], "/graphs/matching_min_vertex_cover.py": ["matching_min_vertex_cover", "get_edges"], "/graphs/minimum_spanning_tree_boruvka.py": ["add_vertex", "add_edge", "distinct_weight", "__str__", "get_edges", "get_vertices", "build", "make_set", "find", "union", "boruvka_mst"], "/graphs/minimum_spanning_tree_kruskal.py": ["kruskal", "find_parent"], "/graphs/minimum_spanning_tree_kruskal2.py": ["make_set", "find_set", "link", "union", "add_node", "add_edge", "kruskal"], "/graphs/minimum_spanning_tree_prims.py": ["PrimsAlgorithm", "get_position", "set_position", "top_to_bottom", "bottom_to_top", "heapify", "deleteMinimum"], "/graphs/minimum_spanning_tree_prims2.py": ["__repr__", "get_parent_position", "get_child_left_position", "get_child_right_position", "is_empty", "push", "extract_min", "update_key", "_bubble_up", "_bubble_down", "_swap_nodes", "add_node", "add_edge", "prims_algo"], "/graphs/multi_heuristic_astar.py": ["minkey", "empty", "put", "remove_element", "top_show", "get", "consistent_heuristic", "heuristic_2", "heuristic_1", "key", "do_something", "valid", "expand_state", "make_common_ground", "multi_a_star"], "/graphs/page_rank.py": ["add_inbound", "add_outbound", "__repr__", "page_rank", "main"], "/graphs/prim.py": ["__lt__", "__repr__", "add_neighbor", "add_edge", "connect", "prim", "prim_heap", "test_vector"], "/graphs/random_graph_generator.py": ["random_graph", "complete_graph"], "/graphs/scc_kosaraju.py": ["dfs", "dfs2", "kosaraju"], "/graphs/strongly_connected_components.py": ["topology_sort", "find_components", "strongly_connected_components"], "/graphs/tarjans_scc.py": ["tarjan", "strong_connect", "create_graph"], "/graphs/tests/test_min_spanning_tree_kruskal.py": ["test_kruskal_successful_result"], "/graphs/tests/test_min_spanning_tree_prim.py": ["test_prim_successful_result"], "/greedy_methods/optimal_merge_pattern.py": ["optimal_merge_pattern"], "/hashes/adler32.py": ["adler32"], "/hashes/chaos_machine.py": ["push", "pull", "xorshift", "reset"], "/hashes/djb2.py": ["djb2"], "/hashes/enigma_machine.py": ["rotator", "engine"], "/hashes/hamming_code.py": ["text_to_bits", "text_from_bits", "emitterConverter", "receptorConverter"], "/hashes/luhn.py": ["is_luhn"], "/hashes/md5.py": ["rearrange", "reformatHex", "pad", "getBlock", "not32", "sum32", "leftrot32", "md5me", "test"], "/hashes/sdbm.py": ["sdbm"], "/hashes/sha1.py": ["rotate", "padding", "split_blocks", "expand_block", "final_hash", "testMatchHashes", "main"], "/hashes/sha256.py": ["preprocessing", "final_hash", "ror", "test_match_hashes", "main"], "/knapsack/greedy_knapsack.py": ["calc_profit"], "/knapsack/knapsack.py": ["knapsack"], "/knapsack/tests/test_greedy_knapsack.py": ["test_sorted", "test_negative_max_weight", "test_negative_profit_value", "test_negative_weight_value", "test_null_max_weight", "test_unequal_list_length"], "/knapsack/tests/test_knapsack.py": ["test_base_case", "test_easy_case", "test_knapsack"], "/linear_algebra/src/conjugate_gradient.py": ["_is_matrix_spd", "_create_spd_matrix", "conjugate_gradient", "test_conjugate_gradient"], "/linear_algebra/src/lib.py": ["__mul__", "__str__", "__add__", "__sub__", "component", "change_component", "set", "copy", "euclidean_length", "angle", "zero_vector", "unit_basis_vector", "axpy", "random_vector", "height", "width", "minor", "cofactor", "determinant", "square_zero_matrix", "random_matrix"], "/linear_algebra/src/polynom_for_points.py": ["points_to_polynomial"], "/linear_algebra/src/power_iteration.py": ["power_iteration", "test_power_iteration"], "/linear_algebra/src/rayleigh_quotient.py": ["is_hermitian", "rayleigh_quotient", "tests"], "/linear_algebra/src/schur_complement.py": ["schur_complement", "test_schur_complement", "test_improper_a_b_dimensions", "test_improper_b_c_dimensions"], "/linear_algebra/src/test_linear_algebra.py": ["test_component", "test_str", "test_size", "test_euclidean_length", "test_add", "test_sub", "test_mul", "test_zeroVector", "test_unitBasisVector", "test_axpy", "test_copy", "test_changeComponent", "test_str_matrix", "test_minor", "test_cofactor", "test_determinant", "test__mul__matrix", "test_change_component_matrix", "test_component_matrix", "test__add__matrix", "test__sub__matrix", "test_squareZeroMatrix"], "/linear_algebra/src/transformations_2d.py": ["scaling", "rotation", "projection", "reflection"], "/machine_learning/astar.py": ["__eq__", "showcell", "show", "get_neigbours", "astar"], "/machine_learning/data_transformations.py": ["normalization", "standardization"], "/machine_learning/decision_tree.py": ["mean_squared_error", "train", "predict", "helper_mean_squared_error_test", "main"], "/machine_learning/forecasting/run.py": ["linear_regression_prediction", "sarimax_predictor", "support_vector_regressor", "interquartile_range_checker", "data_safety_checker"], "/machine_learning/gaussian_naive_bayes.py": ["main"], "/machine_learning/gradient_boosting_regressor.py": ["main"], "/machine_learning/gradient_descent.py": ["_error", "_hypothesis_value", "output", "calculate_hypothesis_value", "summation_of_cost_derivative", "get_cost_derivative", "run_gradient_descent", "test_gradient_descent"], "/machine_learning/k_means_clust.py": ["get_initial_centroids", "centroid_pairwise_dist", "assign_clusters", "revise_centroids", "compute_heterogeneity", "plot_heterogeneity", "kmeans", "ReportGenerator"], "/machine_learning/k_nearest_neighbours.py": ["euclidean_distance", "classifier"], "/machine_learning/linear_discriminant_analysis.py": ["gaussian_distribution", "y_generator", "calculate_mean", "calculate_probabilities", "calculate_variance", "predict_y_values", "accuracy", "valid_input", "main"], "/machine_learning/linear_regression.py": ["collect_dataset", "run_steep_gradient_descent", "sum_of_square_error", "run_linear_regression", "main"], "/machine_learning/local_weighted_learning/local_weighted_learning.py": ["weighted_matrix", "local_weight", "local_weight_regression", "load_data", "get_preds", "plot_preds"], "/machine_learning/logistic_regression.py": ["sigmoid_function", "cost_function", "log_likelihood", "logistic_reg", "predict_prob"], "/machine_learning/multilayer_perceptron_classifier.py": ["wrapper"], "/machine_learning/polymonial_regression.py": ["viz_polymonial"], "/machine_learning/random_forest_classifier.py": ["main"], "/machine_learning/random_forest_regressor.py": ["main"], "/machine_learning/scoring_functions.py": ["mae", "mse", "rmse", "rmsle", "mbd", "manual_accuracy"], "/machine_learning/sequential_minimum_optimization.py": ["fit", "predict", "_check_obey_kkt", "_k", "_e", "_calculate_k_matrix", "_predict", "_choose_alphas", "_choose_a1", "_choose_a2", "_get_new_alpha", "_norm", "_is_unbound", "_is_support", "unbound", "support", "length", "_polynomial", "_linear", "_rbf", "_check", "_get_kernel", "__call__", "__repr__", "count_time", "call_func", "test_cancel_data", "test_demonstration", "test_linear_kernel", "test_rbf_kernel", "plot_partition_boundary"], "/machine_learning/similarity_search.py": ["euclidean", "similarity_search"], "/machine_learning/support_vector_machines.py": ["NuSVC", "Linearsvc", "SVC", "test"], "/machine_learning/word_frequency_functions.py": ["term_frequency", "document_frequency", "inverse_document_frequency", "tf_idf"], "/maths/3n_plus_1.py": ["n31", "test_n31"], "/maths/abs.py": ["abs_val", "test_abs_val"], "/maths/abs_max.py": ["abs_max", "abs_max_sort", "main"], "/maths/abs_min.py": ["abs_min", "main"], "/maths/add.py": ["add"], "/maths/aliquot_sum.py": ["aliquot_sum"], "/maths/allocation_number.py": ["allocation_num"], "/maths/area.py": ["surface_area_cube", "surface_area_sphere", "surface_area_hemisphere", "surface_area_cone", "surface_area_cylinder", "area_rectangle", "area_square", "area_triangle", "area_triangle_three_sides", "area_parallelogram", "area_trapezium", "area_circle", "area_ellipse", "area_rhombus"], "/maths/area_under_curve.py": ["trapezoidal_area", "f"], "/maths/armstrong_numbers.py": ["armstrong_number", "pluperfect_number", "narcissistic_number", "main"], "/maths/average_mean.py": ["mean"], "/maths/average_median.py": ["median", "main"], "/maths/average_mode.py": ["mode"], "/maths/bailey_borwein_plouffe.py": ["bailey_borwein_plouffe", "_subsum"], "/maths/basic_maths.py": ["prime_factors", "number_of_divisors", "sum_of_divisors", "euler_phi"], "/maths/binary_exp_mod.py": ["bin_exp_mod"], "/maths/binary_exponentiation.py": ["binary_exponentiation"], "/maths/binary_exponentiation_2.py": ["b_expo", "b_expo_mod"], "/maths/binary_exponentiation_3.py": ["b_expo", "b_expo_mod"], "/maths/binomial_coefficient.py": ["binomial_coefficient"], "/maths/binomial_distribution.py": ["binomial_distribution"], "/maths/bisection.py": ["equation", "bisection"], "/maths/ceil.py": ["ceil"], "/maths/check_polygon.py": ["check_polygon"], "/maths/chudnovsky_algorithm.py": ["pi"], "/maths/collatz_sequence.py": ["collatz_sequence", "main"], "/maths/combinations.py": ["combinations"], "/maths/decimal_isolate.py": ["decimal_isolate"], "/maths/double_factorial_iterative.py": ["double_factorial"], "/maths/double_factorial_recursive.py": ["double_factorial"], "/maths/entropy.py": ["calculate_prob", "analyze_text", "main"], "/maths/euclidean_distance.py": ["euclidean_distance", "euclidean_distance_no_np", "benchmark"], "/maths/euclidean_gcd.py": ["euclidean_gcd", "euclidean_gcd_recursive", "main"], "/maths/euler_method.py": ["explicit_euler"], "/maths/euler_modified.py": ["euler_modified"], "/maths/eulers_totient.py": ["totient", "test_totient"], "/maths/extended_euclidean_algorithm.py": ["extended_euclidean_algorithm", "main"], "/maths/factorial_iterative.py": ["factorial"], "/maths/factorial_recursive.py": ["factorial"], "/maths/factors.py": ["factors_of_a_number"], "/maths/fermat_little_theorem.py": ["binary_exponentiation"], "/maths/fibonacci.py": ["time_func", "fib_iterative", "fib_recursive", "fib_recursive_term", "fib_memoization", "rec_fn_memoized", "fib_binet"], "/maths/find_max.py": ["find_max"], "/maths/find_max_recursion.py": ["find_max"], "/maths/find_min.py": ["find_min"], "/maths/find_min_recursion.py": ["find_min"], "/maths/floor.py": ["floor"], "/maths/gamma.py": ["gamma", "integrand"], "/maths/gamma_recursive.py": ["gamma", "test_gamma"], "/maths/gaussian.py": ["gaussian"], "/maths/greatest_common_divisor.py": ["greatest_common_divisor", "gcd_by_iterative", "main"], "/maths/greedy_coin_change.py": ["find_minimum_change"], "/maths/hardy_ramanujanalgo.py": ["exactPrimeFactorCount"], "/maths/integration_by_simpson_approx.py": ["f", "simpson_integration"], "/maths/is_ip_v4_address_valid.py": ["is_ip_v4_address_valid"], "/maths/is_square_free.py": ["is_square_free"], "/maths/jaccard_similarity.py": ["jaccard_similariy"], "/maths/kadanes.py": ["negative_exist", "kadanes"], "/maths/karatsuba.py": ["karatsuba", "main"], "/maths/krishnamurthy_number.py": ["factorial", "krishnamurthy"], "/maths/kth_lexicographic_permutation.py": ["kthPermutation"], "/maths/largest_of_very_large_numbers.py": ["res"], "/maths/largest_subarray_sum.py": ["max_sub_array_sum"], "/maths/least_common_multiple.py": ["least_common_multiple_slow", "greatest_common_divisor", "least_common_multiple_fast", "benchmark", "test_lcm_function"], "/maths/line_length.py": ["line_length", "f"], "/maths/lucas_lehmer_primality_test.py": ["lucas_lehmer_test"], "/maths/lucas_series.py": ["recursive_lucas_number", "dynamic_lucas_number"], "/maths/matrix_exponentiation.py": ["__mul__", "modular_exponentiation", "fibonacci_with_matrix_exponentiation", "simple_fibonacci", "matrix_exponentiation_time", "simple_fibonacci_time", "main"], "/maths/max_sum_sliding_window.py": ["max_sum_in_array"], "/maths/median_of_two_arrays.py": ["median_of_two_arrays"], "/maths/miller_rabin.py": ["is_prime"], "/maths/mobius_function.py": ["mobius"], "/maths/modular_exponential.py": ["modular_exponential", "main"], "/maths/monte_carlo.py": ["pi_estimator", "is_in_circle", "area_under_curve_estimator", "area_under_line_estimator_check", "identity_function", "pi_estimator_using_area_under_curve", "function_to_integrate"], "/maths/monte_carlo_dice.py": ["roll", "_str_", "throw_dice"], "/maths/nevilles_method.py": ["neville_interpolate"], "/maths/newton_raphson.py": ["calc_derivative", "newton_raphson"], "/maths/number_of_digits.py": ["num_digits", "num_digits_fast", "num_digits_faster", "benchmark"], "/maths/numerical_integration.py": ["trapezoidal_area", "f"], "/maths/perfect_cube.py": ["perfect_cube"], "/maths/perfect_number.py": ["perfect"], "/maths/perfect_square.py": ["perfect_square", "perfect_square_binary_search"], "/maths/persistence.py": ["multiplicative_persistence", "additive_persistence"], "/maths/pi_monte_carlo_estimation.py": ["is_in_unit_circle", "random_unit_square", "estimate_pi"], "/maths/pollard_rho.py": ["pollard_rho", "rand_fn"], "/maths/polynomial_evaluation.py": ["evaluate_poly", "horner"], "/maths/power_using_recursion.py": ["power"], "/maths/prime_check.py": ["prime_check", "test_primes", "test_not_primes"], "/maths/prime_factors.py": ["prime_factors"], "/maths/prime_numbers.py": ["slow_primes", "primes", "fast_primes"], "/maths/prime_sieve_eratosthenes.py": ["prime_sieve_eratosthenes"], "/maths/primelib.py": ["isPrime", "sieveEr", "getPrimeNumbers", "primeFactorization", "greatestPrimeFactor", "smallestPrimeFactor", "isEven", "isOdd", "goldbach", "gcd", "kgV", "getPrime", "getPrimesBetween", "getDivisors", "isPerfectNumber", "simplifyFraction", "factorial", "fib"], "/maths/proth_number.py": ["proth"], "/maths/pythagoras.py": ["__repr__", "distance", "test_distance"], "/maths/qr_decomposition.py": ["qr_householder"], "/maths/quadratic_equations_complex_numbers.py": ["quadratic_roots", "main"], "/maths/radians.py": ["radians"], "/maths/radix2_fft.py": ["__DFT", "__multiply", "__str__"], "/maths/relu.py": ["relu"], "/maths/runge_kutta.py": ["runge_kutta"], "/maths/segmented_sieve.py": ["sieve"], "/maths/series/arithmetic.py": ["is_arithmetic_series", "arithmetic_mean"], "/maths/series/geometric.py": ["is_geometric_series", "geometric_mean"], "/maths/series/geometric_series.py": ["geometric_series"], "/maths/series/harmonic.py": ["is_harmonic_series", "harmonic_mean"], "/maths/series/harmonic_series.py": ["harmonic_series"], "/maths/series/hexagonal_numbers.py": ["hexagonal_numbers"], "/maths/series/p_series.py": ["p_series"], "/maths/sieve_of_eratosthenes.py": ["prime_sieve"], "/maths/sigmoid.py": ["sigmoid"], "/maths/simpson_rule.py": ["method_2", "make_points", "f", "main"], "/maths/sock_merchant.py": ["sock_merchant"], "/maths/softmax.py": ["softmax"], "/maths/square_root.py": ["fx", "fx_derivative", "get_initial_point", "square_root_iterative"], "/maths/sum_of_arithmetic_series.py": ["sum_of_series", "main"], "/maths/sum_of_digits.py": ["sum_of_digits", "sum_of_digits_recursion", "sum_of_digits_compact", "benchmark"], "/maths/sum_of_geometric_progression.py": ["sum_of_geometric_progression"], "/maths/sylvester_sequence.py": ["sylvester"], "/maths/trapezoidal_rule.py": ["method_1", "make_points", "f", "main"], "/maths/triplet_sum.py": ["make_dataset", "triplet_sum1", "triplet_sum2", "solution_times"], "/maths/two_pointer.py": ["two_pointer"], "/maths/two_sum.py": ["two_sum"], "/maths/ugly_numbers.py": ["ugly_numbers"], "/maths/volume.py": ["vol_cube", "vol_spherical_cap", "vol_spheres_intersect", "vol_cuboid", "vol_cone", "vol_right_circ_cone", "vol_prism", "vol_pyramid", "vol_sphere", "vol_hemisphere", "vol_circular_cylinder", "vol_conical_frustum", "main"], "/maths/zellers_congruence.py": ["zeller"], "/matrix/count_islands_in_matrix.py": ["is_safe", "diffs", "count_islands"], "/matrix/inverse_of_matrix.py": ["inverse_of_matrix"], "/matrix/matrix_class.py": ["columns", "num_rows", "num_columns", "order", "is_square", "identity", "determinant", "is_invertable", "get_minor", "get_cofactor", "minors", "cofactors", "adjugate", "inverse", "__repr__", "__str__", "add_row", "add_column", "__eq__", "__ne__", "__neg__", "__add__", "__sub__", "__mul__", "__pow__", "dot_product"], "/matrix/matrix_operation.py": ["add", "subtract", "scalar_multiply", "multiply", "identity", "transpose", "minor", "determinant", "inverse", "_check_not_integer", "_shape", "_verify_matrix_sizes", "main"], "/matrix/nth_fibonacci_using_matrix_exponentiation.py": ["multiply", "identity", "nth_fibonacci_matrix", "nth_fibonacci_bruteforce", "main"], "/matrix/rotate_matrix.py": ["make_matrix", "rotate_90", "rotate_180", "rotate_270", "transpose", "reverse_row", "reverse_column", "print_matrix"], "/matrix/searching_in_sorted_matrix.py": ["search_in_a_sorted_matrix", "main"], "/matrix/sherman_morrison.py": ["__str__", "single_line", "__repr__", "validateIndices", "__getitem__", "__setitem__", "__add__", "__neg__", "__sub__", "__mul__", "transpose", "ShermanMorrison", "test1", "test2"], "/matrix/spiral_print.py": ["check_matrix", "spiralPrint"], "/matrix/tests/test_matrix_operation.py": ["test_addition", "test_subtraction", "test_multiplication", "test_scalar_multiply", "test_identity", "test_transpose"], "/networking_flow/ford_fulkerson.py": ["BFS", "FordFulkerson"], "/networking_flow/minimum_cut.py": ["BFS", "mincut"], "/neural_network/2_hidden_layers_neural_network.py": ["feedforward", "back_propagation", "train", "predict", "sigmoid", "sigmoid_derivative", "example"], "/neural_network/back_propagation_neural_network.py": ["sigmoid", "initializer", "cal_gradient", "forward_propagation", "back_propagation", "add_layer", "build", "summary", "train", "cal_loss", "plot_loss", "example"], "/neural_network/convolution_neural_network.py": ["save_model", "ReadModel", "sig", "do_round", "convolute", "pooling", "_expand", "_expand_mat", "_calculate_gradient_from_pool", "train", "draw_error", "predict", "convolution"], "/neural_network/perceptron.py": ["training", "sort", "sign"], "/other/activity_selection.py": ["printMaxActivities"], "/other/alternative_list_arrange.py": ["alternative_list_arrange"], "/other/check_strong_password.py": ["strong_password_detector"], "/other/davisb_putnamb_logemannb_loveland.py": ["__str__", "assign", "evaluate", "generate_clause", "generate_formula", "generate_parameters", "find_pure_symbols", "find_unit_clauses", "dpll_algorithm"], "/other/dijkstra_bankers_algorithm.py": ["__processes_resource_summation", "__available_resources", "__need", "__need_index_manager", "main", "__pretty_data"], "/other/doomsday.py": ["get_week_day"], "/other/fischer_yates_shuffle.py": ["fisher_yates_shuffle"], "/other/gauss_easter.py": ["gauss_easter"], "/other/graham_scan.py": ["graham_scan", "angle_comparer", "check_direction"], "/other/greedy.py": ["__repr__", "get_value", "get_name", "get_weight", "value_Weight", "build_menu", "greedy", "test_greedy"], "/other/least_recently_used.py": ["refer", "display", "__repr__"], "/other/lfu_cache.py": ["__repr__", "add", "_position_node", "remove", "__contains__", "get", "set", "decorator", "cache_decorator_inner", "cache_decorator_wrapper", "cache_info"], "/other/linear_congruential_generator.py": ["next_number"], "/other/lru_cache.py": ["__repr__", "add", "remove", "__contains__", "get", "set", "decorator", "cache_decorator_inner", "cache_decorator_wrapper", "cache_info"], "/other/magicdiamondpattern.py": ["floyd", "reverse_floyd", "pretty_print"], "/other/nested_brackets.py": ["is_balanced", "main"], "/other/password_generator.py": ["password_generator", "alternative_password_generator", "random", "random_number", "random_letters", "random_characters", "main"], "/other/scoring_algorithm.py": ["procentual_proximity"], "/other/sdes.py": ["apply_table", "left_shift", "XOR", "apply_sbox", "function"], "/other/tower_of_hanoi.py": ["moveTower", "moveDisk", "main"], "/physics/n_body_simulation.py": ["position", "velocity", "update_velocity", "update_position", "update_system", "update_step", "plot", "update", "example_1", "example_2", "example_3"], "/physics/newtons_second_law_of_motion.py": ["newtons_second_law_of_motion"], "/project_euler/problem_001/sol1.py": ["solution"], "/project_euler/problem_001/sol2.py": ["solution"], "/project_euler/problem_001/sol3.py": ["solution"], "/project_euler/problem_001/sol4.py": ["solution"], "/project_euler/problem_001/sol5.py": ["solution"], "/project_euler/problem_001/sol6.py": ["solution"], "/project_euler/problem_001/sol7.py": ["solution"], "/project_euler/problem_002/sol1.py": ["solution"], "/project_euler/problem_002/sol2.py": ["solution"], "/project_euler/problem_002/sol3.py": ["solution"], "/project_euler/problem_002/sol4.py": ["solution"], "/project_euler/problem_002/sol5.py": ["solution"], "/project_euler/problem_003/sol1.py": ["isprime", "solution"], "/project_euler/problem_003/sol2.py": ["solution"], "/project_euler/problem_003/sol3.py": ["solution"], "/project_euler/problem_004/sol1.py": ["solution"], "/project_euler/problem_004/sol2.py": ["solution"], "/project_euler/problem_005/sol1.py": ["solution"], "/project_euler/problem_005/sol2.py": ["gcd", "lcm", "solution"], "/project_euler/problem_006/sol1.py": ["solution"], "/project_euler/problem_006/sol2.py": ["solution"], "/project_euler/problem_006/sol3.py": ["solution"], "/project_euler/problem_006/sol4.py": ["solution"], "/project_euler/problem_007/sol1.py": ["is_prime", "solution"], "/project_euler/problem_007/sol2.py": ["isprime", "solution"], "/project_euler/problem_007/sol3.py": ["prime_check", "prime_generator", "solution"], "/project_euler/problem_008/sol1.py": ["solution"], "/project_euler/problem_008/sol2.py": ["solution"], "/project_euler/problem_008/sol3.py": ["str_eval", "solution"], "/project_euler/problem_009/sol1.py": ["solution", "solution_fast", "benchmark"], "/project_euler/problem_009/sol2.py": ["solution"], "/project_euler/problem_009/sol3.py": ["solution"], "/project_euler/problem_010/sol1.py": ["is_prime", "solution"], "/project_euler/problem_010/sol2.py": ["is_prime", "prime_generator", "solution"], "/project_euler/problem_010/sol3.py": ["solution"], "/project_euler/problem_011/sol1.py": ["largest_product", "solution"], "/project_euler/problem_011/sol2.py": ["solution"], "/project_euler/problem_012/sol1.py": ["count_divisors", "solution"], "/project_euler/problem_012/sol2.py": ["triangle_number_generator", "count_divisors", "solution"], "/project_euler/problem_013/sol1.py": ["solution"], "/project_euler/problem_014/sol1.py": ["solution"], "/project_euler/problem_014/sol2.py": ["collatz_sequence_length", "solution"], "/project_euler/problem_015/sol1.py": ["solution"], "/project_euler/problem_016/sol1.py": ["solution"], "/project_euler/problem_016/sol2.py": ["solution"], "/project_euler/problem_017/sol1.py": ["solution"], "/project_euler/problem_018/solution.py": ["solution"], "/project_euler/problem_019/sol1.py": ["solution"], "/project_euler/problem_020/sol1.py": ["factorial", "split_and_add", "solution"], "/project_euler/problem_020/sol2.py": ["solution"], "/project_euler/problem_020/sol3.py": ["solution"], "/project_euler/problem_020/sol4.py": ["solution"], "/project_euler/problem_021/sol1.py": ["sum_of_divisors", "solution"], "/project_euler/problem_022/sol1.py": ["solution"], "/project_euler/problem_022/sol2.py": ["solution"], "/project_euler/problem_023/sol1.py": ["solution"], "/project_euler/problem_024/sol1.py": ["solution"], "/project_euler/problem_025/sol1.py": ["fibonacci", "fibonacci_digits_index", "solution"], "/project_euler/problem_025/sol2.py": ["fibonacci_generator", "solution"], "/project_euler/problem_025/sol3.py": ["solution"], "/project_euler/problem_026/sol1.py": ["solution"], "/project_euler/problem_027/sol1.py": ["is_prime", "solution"], "/project_euler/problem_028/sol1.py": ["solution"], "/project_euler/problem_029/sol1.py": ["solution"], "/project_euler/problem_030/sol1.py": ["digitsum", "solution"], "/project_euler/problem_031/sol1.py": ["one_pence", "two_pence", "five_pence", "ten_pence", "twenty_pence", "fifty_pence", "one_pound", "two_pound", "solution"], "/project_euler/problem_031/sol2.py": ["solution"], "/project_euler/problem_032/sol32.py": ["isCombinationValid", "solution"], "/project_euler/problem_033/sol1.py": ["is_digit_cancelling", "fraction_list", "solution"], "/project_euler/problem_034/sol1.py": ["sum_of_digit_factorial", "solution"], "/project_euler/problem_035/sol1.py": ["is_prime", "contains_an_even_digit", "find_circular_primes", "solution"], "/project_euler/problem_036/sol1.py": ["is_palindrome", "solution"], "/project_euler/problem_037/sol1.py": ["is_prime", "list_truncated_nums", "validate", "compute_truncated_primes", "solution"], "/project_euler/problem_038/sol1.py": ["is_9_pandigital", "solution"], "/project_euler/problem_039/sol1.py": ["pythagorean_triple", "solution"], "/project_euler/problem_040/sol1.py": ["solution"], "/project_euler/problem_041/sol1.py": ["is_prime", "solution"], "/project_euler/problem_042/solution42.py": ["solution"], "/project_euler/problem_043/sol1.py": ["is_substring_divisible", "solution"], "/project_euler/problem_044/sol1.py": ["is_pentagonal", "solution"], "/project_euler/problem_045/sol1.py": ["hexagonal_num", "is_pentagonal", "solution"], "/project_euler/problem_046/sol1.py": ["is_prime", "compute_nums", "solution"], "/project_euler/problem_047/sol1.py": ["unique_prime_factors", "upf_len", "equality", "run", "solution"], "/project_euler/problem_048/sol1.py": ["solution"], "/project_euler/problem_049/sol1.py": ["is_prime", "search", "solution"], "/project_euler/problem_050/sol1.py": ["prime_sieve", "solution"], "/project_euler/problem_051/sol1.py": ["prime_sieve", "digit_replacements", "solution"], "/project_euler/problem_052/sol1.py": ["solution"], "/project_euler/problem_053/sol1.py": ["combinations", "solution"], "/project_euler/problem_054/sol1.py": ["hand", "compare_with", "hand_name", "_compare_cards", "_get_hand_type", "_is_flush", "_is_five_high_straight", "_is_straight", "_is_same_kind", "_internal_state", "__repr__", "__str__", "__eq__", "__lt__", "__le__", "__gt__", "__ge__", "__hash__", "solution"], "/project_euler/problem_054/test_poker_hand.py": ["generate_random_hand", "generate_random_hands", "test_hand_is_flush", "test_hand_is_straight", "test_hand_is_five_high_straight", "test_hand_is_same_kind", "test_hand_values", "test_compare_simple", "test_compare_random", "test_hand_sorted", "test_custom_sort_five_high_straight", "test_multiple_calls_five_high_straight", "test_euler_project"], "/project_euler/problem_055/sol1.py": ["is_palindrome", "sum_reverse", "solution"], "/project_euler/problem_056/sol1.py": ["solution"], "/project_euler/problem_057/sol1.py": ["solution"], "/project_euler/problem_058/sol1.py": ["isprime", "solution"], "/project_euler/problem_059/sol1.py": ["try_key", "filter_valid_chars", "filter_common_word", "solution"], "/project_euler/problem_062/sol1.py": ["solution", "get_digits"], "/project_euler/problem_063/sol1.py": ["solution"], "/project_euler/problem_064/sol1.py": ["continuous_fraction_period", "solution"], "/project_euler/problem_065/sol1.py": ["sum_digits", "solution"], "/project_euler/problem_067/sol1.py": ["solution"], "/project_euler/problem_067/sol2.py": ["solution"], "/project_euler/problem_069/sol1.py": ["solution"], "/project_euler/problem_070/sol1.py": ["get_totients", "has_same_digits", "solution"], "/project_euler/problem_071/sol1.py": ["solution"], "/project_euler/problem_072/sol1.py": ["solution"], "/project_euler/problem_072/sol2.py": ["solution"], "/project_euler/problem_074/sol1.py": ["sum_digit_factorials", "chain_length", "solution"], "/project_euler/problem_074/sol2.py": ["factorial", "factorial_sum", "solution"], "/project_euler/problem_075/sol1.py": ["solution"], "/project_euler/problem_076/sol1.py": ["solution"], "/project_euler/problem_077/sol1.py": ["partition", "solution"], "/project_euler/problem_078/sol1.py": ["solution"], "/project_euler/problem_080/sol1.py": ["solution"], "/project_euler/problem_081/sol1.py": ["solution"], "/project_euler/problem_085/sol1.py": ["solution"], "/project_euler/problem_086/sol1.py": ["solution"], "/project_euler/problem_087/sol1.py": ["solution"], "/project_euler/problem_089/sol1.py": ["parse_roman_numerals", "generate_roman_numerals", "solution"], "/project_euler/problem_091/sol1.py": ["is_right", "solution"], "/project_euler/problem_092/sol1.py": ["next_number", "chain", "solution"], "/project_euler/problem_097/sol1.py": ["solution"], "/project_euler/problem_099/sol1.py": ["solution"], "/project_euler/problem_101/sol1.py": ["solve", "interpolate", "interpolated_func", "question_function", "solution"], "/project_euler/problem_102/sol1.py": ["vector_product", "contains_origin", "solution"], "/project_euler/problem_107/sol1.py": ["add_edge", "prims_algorithm", "solution"], "/project_euler/problem_109/sol1.py": ["solution"], "/project_euler/problem_112/sol1.py": ["check_bouncy", "solution"], "/project_euler/problem_113/sol1.py": ["choose", "non_bouncy_exact", "non_bouncy_upto", "solution"], "/project_euler/problem_119/sol1.py": ["digit_sum", "solution"], "/project_euler/problem_120/sol1.py": ["solution"], "/project_euler/problem_121/sol1.py": ["solution"], "/project_euler/problem_123/sol1.py": ["sieve", "solution"], "/project_euler/problem_125/sol1.py": ["is_palindrome", "solution"], "/project_euler/problem_129/sol1.py": ["least_divisible_repunit", "solution"], "/project_euler/problem_135/sol1.py": ["solution"], "/project_euler/problem_144/sol1.py": ["next_point", "solution"], "/project_euler/problem_145/sol1.py": ["check_if_odd", "find_reverse_number", "solution"], "/project_euler/problem_173/sol1.py": ["solution"], "/project_euler/problem_174/sol1.py": ["solution"], "/project_euler/problem_180/sol1.py": ["is_sq", "add_three", "solution"], "/project_euler/problem_188/sol1.py": ["_modexpt", "solution"], "/project_euler/problem_191/sol1.py": ["_calculate", "solution"], "/project_euler/problem_203/sol1.py": ["get_pascal_triangle_unique_coefficients", "get_primes_squared", "get_squared_primes_to_use", "get_squarefree", "solution"], "/project_euler/problem_205/sol1.py": ["total_frequency_distribution", "solution"], "/project_euler/problem_206/sol1.py": ["is_square_form", "solution"], "/project_euler/problem_207/sol1.py": ["check_partition_perfect", "solution"], "/project_euler/problem_234/sol1.py": ["prime_sieve", "solution"], "/project_euler/problem_301/sol1.py": ["solution"], "/project_euler/problem_493/sol1.py": ["solution"], "/project_euler/problem_551/sol1.py": ["next_term", "compute", "add", "solution"], "/project_euler/problem_686/sol1.py": ["log_difference", "solution"], "/quantum/deutsch_jozsa.py": ["dj_oracle", "dj_algorithm", "deutsch_jozsa"], "/quantum/half_adder.py": ["half_adder"], "/quantum/not_gate.py": ["single_qubit_measure"], "/quantum/quantum_entanglement.py": ["quantum_entanglement"], "/quantum/ripple_adder_classic.py": ["store_two_classics", "full_adder", "ripple_adder"], "/quantum/single_qubit_measure.py": ["single_qubit_measure"], "/scheduling/first_come_first_served.py": ["calculate_waiting_times", "calculate_turnaround_times", "calculate_average_turnaround_time", "calculate_average_waiting_time"], "/scheduling/round_robin.py": ["calculate_waiting_times", "calculate_turn_around_times"], "/scheduling/shortest_job_first.py": ["calculate_waitingtime", "calculate_turnaroundtime", "calculate_average_times"], "/scripts/build_directory_md.py": ["good_file_paths", "md_prefix", "print_path", "print_directory_md"], "/scripts/validate_solutions.py": ["convert_path_to_module", "all_solution_file_paths", "get_files_url", "added_solution_file_path", "collect_solution_file_paths", "test_project_euler"], "/searches/binary_search.py": ["bisect_left", "bisect_right", "insort_left", "insort_right", "binary_search", "binary_search_std_lib", "binary_search_by_recursion"], "/searches/binary_tree_traversal.py": ["build_tree", "pre_order", "in_order", "post_order", "level_order", "level_order_actual", "pre_order_iter", "in_order_iter", "post_order_iter", "prompt"], "/searches/double_linear_search.py": ["double_linear_search"], "/searches/double_linear_search_recursion.py": ["search"], "/searches/fibonacci_search.py": ["fibonacci", "fibonacci_search"], "/searches/hill_climbing.py": ["score", "get_neighbors", "__hash__", "__eq__", "__str__", "hill_climbing", "test_f1", "test_f2"], "/searches/interpolation_search.py": ["interpolation_search", "interpolation_search_by_recursion", "__assert_sorted"], "/searches/jump_search.py": ["jump_search"], "/searches/linear_search.py": ["linear_search", "rec_linear_search"], "/searches/quick_select.py": ["_partition", "quick_select"], "/searches/sentinel_linear_search.py": ["sentinel_linear_search"], "/searches/simple_binary_search.py": ["binary_search"], "/searches/simulated_annealing.py": ["simulated_annealing", "test_f1", "test_f2"], "/searches/tabu_search.py": ["generate_neighbours", "generate_first_solution", "find_neighborhood", "tabu_search", "main"], "/searches/ternary_search.py": ["lin_search", "ite_ternary_search", "rec_ternary_search"], "/sorts/bead_sort.py": ["bead_sort"], "/sorts/bitonic_sort.py": ["comp_and_swap", "bitonic_merge", "bitonic_sort"], "/sorts/bogo_sort.py": ["bogo_sort", "is_sorted"], "/sorts/bubble_sort.py": ["bubble_sort"], "/sorts/bucket_sort.py": ["bucket_sort"], "/sorts/cocktail_shaker_sort.py": ["cocktail_shaker_sort"], "/sorts/comb_sort.py": ["comb_sort"], "/sorts/counting_sort.py": ["counting_sort", "counting_sort_string"], "/sorts/cycle_sort.py": ["cycle_sort"], "/sorts/double_sort.py": ["double_sort"], "/sorts/dutch_national_flag_sort.py": ["dutch_national_flag_sort"], "/sorts/exchange_sort.py": ["exchange_sort"], "/sorts/external_sort.py": ["write_block", "get_block_filenames", "split", "cleanup", "select", "get_dict", "refresh", "unshift", "merge", "get_file_handles", "sort", "get_number_blocks", "parse_memory", "main"], "/sorts/gnome_sort.py": ["gnome_sort"], "/sorts/heap_sort.py": ["heapify", "heap_sort"], "/sorts/insertion_sort.py": ["insertion_sort"], "/sorts/intro_sort.py": ["insertion_sort", "heapify", "heap_sort", "median_of_3", "partition", "sort", "intro_sort"], "/sorts/iterative_merge_sort.py": ["merge", "iter_merge_sort"], "/sorts/merge_insertion_sort.py": ["merge_insertion_sort", "binary_search_insertion", "sortlist_2d", "merge"], "/sorts/merge_sort.py": ["merge_sort", "merge", "_merge"], "/sorts/msd_radix_sort.py": ["msd_radix_sort", "_msd_radix_sort", "msd_radix_sort_inplace", "_msd_radix_sort_inplace"], "/sorts/natural_sort.py": ["natural_sort", "alphanum_key"], "/sorts/odd_even_sort.py": ["odd_even_sort"], "/sorts/odd_even_transposition_parallel.py": ["oeProcess", "OddEvenTransposition", "main"], "/sorts/odd_even_transposition_single_threaded.py": ["odd_even_transposition"], "/sorts/pancake_sort.py": ["pancake_sort"], "/sorts/patience_sort.py": ["__lt__", "__eq__", "patience_sort"], "/sorts/pigeon_sort.py": ["pigeon_sort"], "/sorts/pigeonhole_sort.py": ["pigeonhole_sort", "main"], "/sorts/quick_sort.py": ["quick_sort"], "/sorts/quick_sort_3_partition.py": ["quick_sort_3partition", "quick_sort_lomuto_partition", "lomuto_partition", "three_way_radix_quicksort"], "/sorts/radix_sort.py": ["radix_sort"], "/sorts/random_normal_distribution_quicksort.py": ["_inPlaceQuickSort", "_inPlacePartition"], "/sorts/random_pivot_quick_sort.py": ["partition", "quick_sort_random", "main"], "/sorts/recursive_bubble_sort.py": ["bubble_sort"], "/sorts/recursive_insertion_sort.py": ["rec_insertion_sort", "insert_next"], "/sorts/recursive_mergesort_array.py": ["merge"], "/sorts/recursive_quick_sort.py": ["quick_sort"], "/sorts/selection_sort.py": ["selection_sort"], "/sorts/shell_sort.py": ["shell_sort"], "/sorts/slowsort.py": ["slowsort"], "/sorts/stooge_sort.py": ["stooge_sort", "stooge"], "/sorts/strand_sort.py": ["strand_sort"], "/sorts/tim_sort.py": ["binary_search", "insertion_sort", "merge", "tim_sort", "main"], "/sorts/topological_sort.py": ["topological_sort"], "/sorts/tree_sort.py": ["insert", "inorder", "tree_sort"], "/sorts/unknown_sort.py": ["merge_sort"], "/sorts/wiggle_sort.py": ["wiggle_sort"], "/strings/aho_corasick.py": ["find_next_state", "add_keyword", "set_fail_transitions", "search_in"], "/strings/alternative_string_arrange.py": ["alternative_string_arrange"], "/strings/anagrams.py": ["signature", "anagram"], "/strings/autocomplete_using_trie.py": ["insert_word", "find_word", "_elements", "autocomplete_using_trie", "main"], "/strings/boyer_moore_search.py": ["match_in_pattern", "mismatch_in_text", "bad_character_heuristic"], "/strings/can_string_be_rearranged_as_palindrome.py": ["can_string_be_rearranged_as_palindrome_counter", "can_string_be_rearranged_as_palindrome", "benchmark"], "/strings/capitalize.py": ["capitalize"], "/strings/check_anagrams.py": ["check_anagrams"], "/strings/check_pangram.py": ["check_pangram", "check_pangram_faster", "benchmark"], "/strings/credit_card_validator.py": ["validate_initial_digits", "luhn_validation", "validate_credit_card_number"], "/strings/detecting_english_programmatically.py": ["loadDictionary", "getEnglishCount", "removeNonLetters", "isEnglish"], "/strings/frequency_finder.py": ["getLetterCount", "getItemAtIndexZero", "getFrequencyOrder", "englishFreqMatchScore"], "/strings/indian_phone_validator.py": ["indian_phone_validator"], "/strings/is_contains_unique_chars.py": ["is_contains_unique_chars"], "/strings/is_palindrome.py": ["is_palindrome"], "/strings/jaro_winkler.py": ["jaro_winkler", "get_matched_characters"], "/strings/join.py": ["join"], "/strings/knuth_morris_pratt.py": ["kmp", "get_failure_array"], "/strings/levenshtein_distance.py": ["levenshtein_distance"], "/strings/lower.py": ["lower"], "/strings/manacher.py": ["palindromic_string"], "/strings/min_cost_string_conversion.py": ["compute_transform_tables", "assemble_transformation"], "/strings/naive_string_search.py": ["naive_pattern_search"], "/strings/palindrome.py": ["is_palindrome", "is_palindrome_recursive", "is_palindrome_slice"], "/strings/prefix_function.py": ["prefix_function", "longest_prefix"], "/strings/rabin_karp.py": ["rabin_karp", "test_rabin_karp"], "/strings/remove_duplicate.py": ["remove_duplicates"], "/strings/reverse_letters.py": ["reverse_letters"], "/strings/reverse_long_words.py": ["reverse_long_words"], "/strings/reverse_words.py": ["reverse_words"], "/strings/split.py": ["split"], "/strings/upper.py": ["upper"], "/strings/wildcard_pattern_matching.py": ["match_pattern"], "/strings/word_occurrence.py": ["word_occurence"], "/strings/word_patterns.py": ["get_word_pattern"], "/strings/z_function.py": ["z_function", "go_next", "find_pattern"], "/web_programming/co2_emission.py": ["fetch_last_half_hour", "fetch_from_to"], "/web_programming/covid_stats_via_xpath.py": ["covid_stats"], "/web_programming/crawl_google_scholar_citation.py": ["get_citation"], "/web_programming/currency_converter.py": ["convert_currency"], "/web_programming/current_stock_price.py": ["stock_price"], "/web_programming/current_weather.py": ["current_weather", "weather_forecast", "weather_onecall"], "/web_programming/daily_horoscope.py": ["horoscope"], "/web_programming/download_images_from_google_query.py": ["download_images_from_google_query"], "/web_programming/emails_from_url.py": ["handle_starttag", "get_domain_name", "get_sub_domain_name", "emails_from_url"], "/web_programming/fetch_bbc_news.py": ["fetch_bbc_news"], "/web_programming/fetch_github_info.py": ["fetch_github_info"], "/web_programming/fetch_jobs.py": ["fetch_jobs"], "/web_programming/get_imdb_top_250_movies_csv.py": ["get_imdb_top_250_movies", "write_movies"], "/web_programming/get_imdbtop.py": ["get_movie_data_from_soup", "get_imdb_top_movies"], "/web_programming/get_top_hn_posts.py": ["get_hackernews_story", "hackernews_top_stories", "hackernews_top_stories_as_markdown"], "/web_programming/get_user_tweets.py": ["get_all_tweets"], "/web_programming/giphy.py": ["get_gifs"], "/web_programming/instagram_crawler.py": ["extract_user_profile", "get_json", "__repr__", "__str__", "username", "fullname", "biography", "email", "website", "number_of_followers", "number_of_followings", "number_of_posts", "profile_picture_url", "is_verified", "is_private", "test_instagram_user"], "/web_programming/instagram_video.py": ["download_video"], "/web_programming/nasa_data.py": ["get_apod_data", "save_apod", "get_archive_data"], "/web_programming/random_anime_character.py": ["save_image", "random_anime_character"], "/web_programming/recaptcha_verification.py": ["login_using_recaptcha"], "/web_programming/reddit.py": ["get_subreddit_data"], "/web_programming/search_books_by_isbn.py": ["get_openlibrary_data", "summarize_book"], "/web_programming/slack_message.py": ["send_slack_message"], "/web_programming/test_fetch_github_info.py": ["test_fetch_github_info", "json", "mock_response"], "/web_programming/world_covid19_stats.py": ["world_covid19_stats"]}}